{
	"header": {
		"title": "Making Multiplayer HTML5 Game with Node.js",
		"References": "https://www.youtube.com/watch?v=PfSwUOBL1YQ",
		"classes": {
			"class_1": "Setup and Sendding Files",
			"class_2": "WebSocket Communication",
			"class_3": "Multiple WebSocket Connections",
			"class_4": "Keyboard Interactivity",
			"class_5": "OOP & Bullet",
			"class_6": "Chat & Debug Server"
		}
	},
	"tecnologies": {
		"server": "Node.js",
		"libInstaller": "NPM",
		"textEditor": "Notepad++",
		"client": "Chrome",
		"mainLibraries": {
			"delivFiles": "Express.js",
			"communication": "socket.io"
		}
	}
}